[{"_id":"124928828","date":"1602461222","price":0.00442275,"pair":"ltcbtc","amount":0.239381,"__v":0},{"_id":"124928837","date":"1602461260","price":0.00442226,"pair":"ltcbtc","amount":45,"__v":0},{"_id":"124928992","date":"1602461606","price":0.00442776,"pair":"ltcbtc","amount":0.818094,"__v":0},{"_id":"124928993","date":"1602461627","price":0.00443,"pair":"ltcbtc","amount":0.419506,"__v":0},{"_id":"124929629","date":"1602463573","price":0.00440815,"pair":"ltcbtc","amount":29.92046,"__v":0},{"_id":"124929634","date":"1602463573","price":0.00440566,"pair":"ltcbtc","amount":20,"__v":0},{"_id":"124929630","date":"1602463573","price":0.00440815,"pair":"ltcbtc","amount":8,"__v":0},{"_id":"124929694","date":"1602463891","price":0.00441112,"pair":"ltcbtc","amount":2.99304089,"__v":0},{"_id":"124929839","date":"1602464285","price":0.00441444,"pair":"ltcbtc","amount":33.64427,"__v":0},{"_id":"124929838","date":"1602464285","price":0.00441444,"pair":"ltcbtc","amount":29.86358,"__v":0},{"_id":"124929840","date":"1602464285","price":0.00441444,"pair":"ltcbtc","amount":65.85373,"__v":0},{"_id":"124929960","date":"1602464744","price":0.0044197,"pair":"ltcbtc","amount":35.70318,"__v":0},{"_id":"124929959","date":"1602464744","price":0.0044197,"pair":"ltcbtc","amount":19.29682,"__v":0},{"_id":"124929957","date":"1602464744","price":0.0044197,"pair":"ltcbtc","amount":29.84382,"__v":0},{"_id":"124929958","date":"1602464744","price":0.0044197,"pair":"ltcbtc","amount":25.15618,"__v":0},{"_id":"124930104","date":"1602465512","price":0.00441437,"pair":"ltcbtc","amount":5,"__v":0},{"_id":"124930124","date":"1602465595","price":0.00441772,"pair":"ltcbtc","amount":0.419069,"__v":0},{"_id":"124930253","date":"1602465947","price":0.00441011,"pair":"ltcbtc","amount":1.965714,"__v":0},{"_id":"124930659","date":"1602466956","price":0.00440815,"pair":"ltcbtc","amount":8,"__v":0},{"_id":"124931001","date":"1602468181","price":0.00441311,"pair":"ltcbtc","amount":37.85373,"__v":0},{"_id":"124931000","date":"1602468181","price":0.00441311,"pair":"ltcbtc","amount":35,"__v":0},{"_id":"124931004","date":"1602468182","price":0.00441311,"pair":"ltcbtc","amount":26.47227,"__v":0},{"_id":"124931039","date":"1602468328","price":0.00441539,"pair":"ltcbtc","amount":1.887482,"__v":0},{"_id":"124931160","date":"1602468931","price":0.00440681,"pair":"ltcbtc","amount":15,"__v":0},{"_id":"124931307","date":"1602469499","price":0.00440511,"pair":"ltcbtc","amount":85.40614,"__v":0},{"_id":"124931330","date":"1602469571","price":0.0044,"pair":"ltcbtc","amount":99.7369991,"__v":0},{"_id":"124931329","date":"1602469571","price":0.0044,"pair":"ltcbtc","amount":62.3711909,"__v":0},{"_id":"124931337","date":"1602469597","price":0.00439565,"pair":"ltcbtc","amount":99.841,"__v":0},{"_id":"124931469","date":"1602470230","price":0.00439923,"pair":"ltcbtc","amount":0.237009,"__v":0},{"_id":"124931531","date":"1602470384","price":0.00439617,"pair":"ltcbtc","amount":0.7896,"__v":0},{"_id":"124931575","date":"1602470521","price":0.00439875,"pair":"ltcbtc","amount":0.40000667,"__v":0},{"_id":"124931748","date":"1602471235","price":0.00440689,"pair":"ltcbtc","amount":10.528146,"__v":0},{"_id":"124932210","date":"1602473183","price":0.00440261,"pair":"ltcbtc","amount":0.519816,"__v":0},{"_id":"124932298","date":"1602473516","price":0.00440461,"pair":"ltcbtc","amount":0.84001401,"__v":0},{"_id":"124932353","date":"1602473641","price":0.00440316,"pair":"ltcbtc","amount":1.22002034,"__v":0},{"_id":"124932498","date":"1602474137","price":0.00440156,"pair":"ltcbtc","amount":0.273929,"__v":0},{"_id":"124932583","date":"1602474375","price":0.00439482,"pair":"ltcbtc","amount":0.348823,"__v":0},{"_id":"124932613","date":"1602474573","price":0.00439343,"pair":"ltcbtc","amount":0.614018,"__v":0},{"_id":"124932700","date":"1602474875","price":0.00439868,"pair":"ltcbtc","amount":11.419073,"__v":0},{"_id":"124932755","date":"1602475065","price":0.00440006,"pair":"ltcbtc","amount":1.52413,"__v":0},{"_id":"124932758","date":"1602475079","price":0.00439711,"pair":"ltcbtc","amount":0.256235,"__v":0},{"_id":"124932760","date":"1602475085","price":0.00439711,"pair":"ltcbtc","amount":1.93716045,"__v":0},{"_id":"124932787","date":"1602475199","price":0.00439757,"pair":"ltcbtc","amount":29.96404,"__v":0},{"_id":"124932792","date":"1602475199","price":0.00439947,"pair":"ltcbtc","amount":29.93104,"__v":0},{"_id":"124932797","date":"1602475199","price":0.00440214,"pair":"ltcbtc","amount":29.91294,"__v":0},{"_id":"124932789","date":"1602475199","price":0.00439882,"pair":"ltcbtc","amount":99.872,"__v":0},{"_id":"124932788","date":"1602475199","price":0.00439882,"pair":"ltcbtc","amount":29.96291,"__v":0},{"_id":"124932791","date":"1602475199","price":0.00439919,"pair":"ltcbtc","amount":34.015,"__v":0},{"_id":"124932794","date":"1602475199","price":0.00440095,"pair":"ltcbtc","amount":29.93399,"__v":0},{"_id":"124932790","date":"1602475199","price":0.00439896,"pair":"ltcbtc","amount":8,"__v":0},{"_id":"124932793","date":"1602475199","price":0.0044,"pair":"ltcbtc","amount":97.6059,"__v":0},{"_id":"124932796","date":"1602475199","price":0.00440213,"pair":"ltcbtc","amount":367.43,"__v":0},{"_id":"124932798","date":"1602475199","price":0.00440741,"pair":"ltcbtc","amount":241.16989763,"__v":0},{"_id":"124932795","date":"1602475199","price":0.00440096,"pair":"ltcbtc","amount":199,"__v":0},{"_id":"124932898","date":"1602475512","price":0.00439415,"pair":"ltcbtc","amount":23.546905,"__v":0},{"_id":"124932960","date":"1602475708","price":0.00439477,"pair":"ltcbtc","amount":0.236977,"__v":0},{"_id":"124933128","date":"1602476361","price":0.00438101,"pair":"ltcbtc","amount":35.954,"__v":0},{"_id":"124933129","date":"1602476362","price":0.00438351,"pair":"ltcbtc","amount":8,"__v":0},{"_id":"124933137","date":"1602476429","price":0.00437692,"pair":"ltcbtc","amount":65,"__v":0},{"_id":"124933188","date":"1602476529","price":0.00437421,"pair":"ltcbtc","amount":45.438,"__v":0},{"_id":"124933187","date":"1602476529","price":0.00437421,"pair":"ltcbtc","amount":55,"__v":0},{"_id":"124933255","date":"1602476718","price":0.00438034,"pair":"ltcbtc","amount":1.09376,"__v":0},{"_id":"124933288","date":"1602476825","price":0.00438115,"pair":"ltcbtc","amount":7.07453,"__v":0},{"_id":"124933381","date":"1602477349","price":0.0043883,"pair":"ltcbtc","amount":0.367264,"__v":0},{"_id":"124933423","date":"1602477533","price":0.00439652,"pair":"ltcbtc","amount":1.662694,"__v":0},{"_id":"124933484","date":"1602477982","price":0.0043984,"pair":"ltcbtc","amount":1.040726,"__v":0},{"_id":"124933575","date":"1602478358","price":0.00439445,"pair":"ltcbtc","amount":1.442234,"__v":0},{"_id":"124933988","date":"1602479495","price":0.00440122,"pair":"ltcbtc","amount":0.287452,"__v":0},{"_id":"124934423","date":"1602480951","price":0.0044065,"pair":"ltcbtc","amount":9.668454,"__v":0},{"_id":"124934766","date":"1602482019","price":0.00440562,"pair":"ltcbtc","amount":1.416941,"__v":0},{"_id":"124934827","date":"1602482200","price":0.00440767,"pair":"ltcbtc","amount":0.5,"__v":0},{"_id":"124934828","date":"1602482200","price":0.00440827,"pair":"ltcbtc","amount":0.5,"__v":0},{"_id":"124934829","date":"1602482200","price":0.00440844,"pair":"ltcbtc","amount":0.5,"__v":0},{"_id":"124934830","date":"1602482200","price":0.00440929,"pair":"ltcbtc","amount":0.476361,"__v":0},{"_id":"124935211","date":"1602483379","price":0.00439985,"pair":"ltcbtc","amount":5.018057,"__v":0},{"_id":"124935391","date":"1602483709","price":0.00440027,"pair":"ltcbtc","amount":1.434402,"__v":0},{"_id":"124935447","date":"1602483813","price":0.00440058,"pair":"ltcbtc","amount":0.473039,"__v":0},{"_id":"124935500","date":"1602483953","price":0.00440011,"pair":"ltcbtc","amount":1.681412,"__v":0},{"_id":"124935550","date":"1602484013","price":0.00440048,"pair":"ltcbtc","amount":0.236676,"__v":0},{"_id":"124935608","date":"1602484134","price":0.00439567,"pair":"ltcbtc","amount":6.65,"__v":0},{"_id":"124935921","date":"1602484839","price":0.00440221,"pair":"ltcbtc","amount":0.236592,"__v":0},{"_id":"124935975","date":"1602484965","price":0.00440157,"pair":"ltcbtc","amount":0.420661,"__v":0},{"_id":"124936123","date":"1602485268","price":0.00440336,"pair":"ltcbtc","amount":0.69423,"__v":0},{"_id":"124936161","date":"1602485324","price":0.00440258,"pair":"ltcbtc","amount":0.955037,"__v":0},{"_id":"124936260","date":"1602485569","price":0.00440142,"pair":"ltcbtc","amount":8.321321,"__v":0},{"_id":"124936446","date":"1602485956","price":0.00439922,"pair":"ltcbtc","amount":0.28553,"__v":0},{"_id":"124936648","date":"1602486068","price":0.00439687,"pair":"ltcbtc","amount":8.93430851,"__v":0},{"_id":"124936647","date":"1602486068","price":0.00439652,"pair":"ltcbtc","amount":34.788639,"__v":0},{"_id":"124936646","date":"1602486068","price":0.0043964,"pair":"ltcbtc","amount":36.784,"__v":0},{"_id":"124936645","date":"1602486068","price":0.00439623,"pair":"ltcbtc","amount":30.10526,"__v":0},{"_id":"124936644","date":"1602486068","price":0.00439469,"pair":"ltcbtc","amount":0.5,"__v":0},{"_id":"124936776","date":"1602486173","price":0.00440043,"pair":"ltcbtc","amount":0.629617,"__v":0},{"_id":"124937034","date":"1602486537","price":0.00440726,"pair":"ltcbtc","amount":0.570398,"__v":0},{"_id":"124937037","date":"1602486542","price":0.00440726,"pair":"ltcbtc","amount":0.698175,"__v":0},{"_id":"124937102","date":"1602486678","price":0.00440687,"pair":"ltcbtc","amount":0.840866,"__v":0},{"_id":"124937352","date":"1602487108","price":0.00440245,"pair":"ltcbtc","amount":0.241916,"__v":0},{"_id":"124937380","date":"1602487174","price":0.00441017,"pair":"ltcbtc","amount":99.791,"__v":0},{"_id":"124937802","date":"1602487912","price":0.0044234,"pair":"ltcbtc","amount":9.9,"__v":0},{"_id":"124937804","date":"1602487912","price":0.0044234,"pair":"ltcbtc","amount":19.423,"__v":0},{"_id":"124937803","date":"1602487912","price":0.0044234,"pair":"ltcbtc","amount":70,"__v":0},{"_id":"124937806","date":"1602487912","price":0.0044203,"pair":"ltcbtc","amount":2.41,"__v":0},{"_id":"124937849","date":"1602487993","price":0.00442915,"pair":"ltcbtc","amount":99.1,"__v":0},{"_id":"124937992","date":"1602488221","price":0.0044333,"pair":"ltcbtc","amount":0.333721,"__v":0},{"_id":"124938256","date":"1602488537","price":0.0044551,"pair":"ltcbtc","amount":98.367,"__v":0},{"_id":"124938285","date":"1602488583","price":0.00444883,"pair":"ltcbtc","amount":65,"__v":0},{"_id":"124938287","date":"1602488583","price":0.00444883,"pair":"ltcbtc","amount":33.567,"__v":0},{"_id":"124938288","date":"1602488584","price":0.00444207,"pair":"ltcbtc","amount":1.68021,"__v":0},{"_id":"124938298","date":"1602488615","price":0.00444723,"pair":"ltcbtc","amount":3.23637,"__v":0},{"_id":"124938299","date":"1602488615","price":0.00444723,"pair":"ltcbtc","amount":2.2472,"__v":0},{"_id":"124938303","date":"1602488616","price":0.00444723,"pair":"ltcbtc","amount":8.27199,"__v":0},{"_id":"124938305","date":"1602488616","price":0.00444723,"pair":"ltcbtc","amount":5.75279,"__v":0},{"_id":"124938300","date":"1602488616","price":0.00444723,"pair":"ltcbtc","amount":6.51129,"__v":0},{"_id":"124938307","date":"1602488616","price":0.00444723,"pair":"ltcbtc","amount":6.73409,"__v":0},{"_id":"124938302","date":"1602488616","price":0.00444723,"pair":"ltcbtc","amount":2.05394,"__v":0},{"_id":"124938304","date":"1602488616","price":0.00444723,"pair":"ltcbtc","amount":11.95289,"__v":0},{"_id":"124938306","date":"1602488616","price":0.00444723,"pair":"ltcbtc","amount":29.63278,"__v":0},{"_id":"124938301","date":"1602488616","price":0.00444723,"pair":"ltcbtc","amount":12.16121,"__v":0},{"_id":"124938323","date":"1602488639","price":0.00444971,"pair":"ltcbtc","amount":34.224,"__v":0},{"_id":"124938337","date":"1602488647","price":0.00444576,"pair":"ltcbtc","amount":2.854838,"__v":0},{"_id":"124938374","date":"1602488679","price":0.00444195,"pair":"ltcbtc","amount":98.764,"__v":0},{"_id":"124938411","date":"1602488739","price":0.00444501,"pair":"ltcbtc","amount":0.867613,"__v":0},{"_id":"124938489","date":"1602488887","price":0.00443815,"pair":"ltcbtc","amount":2.643135,"__v":0},{"_id":"124938706","date":"1602489220","price":0.00442927,"pair":"ltcbtc","amount":1.30045,"__v":0},{"_id":"124938977","date":"1602489675","price":0.0044311,"pair":"ltcbtc","amount":0.9,"__v":0},{"_id":"124939156","date":"1602490003","price":0.00443349,"pair":"ltcbtc","amount":1,"__v":0},{"_id":"124939518","date":"1602490660","price":0.00442817,"pair":"ltcbtc","amount":0.304113,"__v":0},{"_id":"124939520","date":"1602490682","price":0.00442817,"pair":"ltcbtc","amount":0.526587,"__v":0},{"_id":"124939940","date":"1602491155","price":0.00443498,"pair":"ltcbtc","amount":0.355473,"__v":0},{"_id":"124940056","date":"1602491268","price":0.00443303,"pair":"ltcbtc","amount":2.376415,"__v":0},{"_id":"124940211","date":"1602491387","price":0.00444123,"pair":"ltcbtc","amount":0.228321,"__v":0},{"_id":"124940237","date":"1602491404","price":0.00444001,"pair":"ltcbtc","amount":4.366142,"__v":0},{"_id":"124940611","date":"1602491887","price":0.00443499,"pair":"ltcbtc","amount":4.0527,"__v":0},{"_id":"124940720","date":"1602492059","price":0.00444381,"pair":"ltcbtc","amount":0.38939,"__v":0},{"_id":"124940831","date":"1602492155","price":0.00444427,"pair":"ltcbtc","amount":10,"__v":0},{"_id":"124940846","date":"1602492213","price":0.00443983,"pair":"ltcbtc","amount":0.308744,"__v":0},{"_id":"124940847","date":"1602492217","price":0.00444427,"pair":"ltcbtc","amount":0.66744,"__v":0},{"_id":"124940890","date":"1602492322","price":0.00443833,"pair":"ltcbtc","amount":21.036574,"__v":0},{"_id":"124940888","date":"1602492322","price":0.00443983,"pair":"ltcbtc","amount":0.000006,"__v":0},{"_id":"124940889","date":"1602492322","price":0.00443973,"pair":"ltcbtc","amount":29.683844,"__v":0},{"_id":"124940886","date":"1602492322","price":0.00443983,"pair":"ltcbtc","amount":7.69125,"__v":0},{"_id":"124940919","date":"1602492366","price":0.00443833,"pair":"ltcbtc","amount":28.8293,"__v":0},{"_id":"124940917","date":"1602492366","price":0.00443833,"pair":"ltcbtc","amount":75,"__v":0},{"_id":"124940918","date":"1602492366","price":0.00443833,"pair":"ltcbtc","amount":9.9,"__v":0},{"_id":"124940916","date":"1602492366","price":0.00443833,"pair":"ltcbtc","amount":45,"__v":0},{"_id":"124940921","date":"1602492367","price":0.00443833,"pair":"ltcbtc","amount":0.004126,"__v":0},{"_id":"124940920","date":"1602492367","price":0.00443833,"pair":"ltcbtc","amount":19.23,"__v":0},{"_id":"124941324","date":"1602493087","price":0.00443738,"pair":"ltcbtc","amount":1.401843,"__v":0},{"_id":"124941476","date":"1602493253","price":0.00443301,"pair":"ltcbtc","amount":14.401,"__v":0},{"_id":"124941475","date":"1602493253","price":0.00443301,"pair":"ltcbtc","amount":85,"__v":0},{"_id":"124941863","date":"1602494028","price":0.00443428,"pair":"ltcbtc","amount":0.339003,"__v":0},{"_id":"124941962","date":"1602494151","price":0.00443536,"pair":"ltcbtc","amount":0.284415,"__v":0},{"_id":"124943433","date":"1602495672","price":0.004418,"pair":"ltcbtc","amount":1.93716045,"__v":0},{"_id":"124943859","date":"1602496162","price":0.00441426,"pair":"ltcbtc","amount":20,"__v":0},{"_id":"124944224","date":"1602496532","price":0.0044227,"pair":"ltcbtc","amount":34.947,"__v":0},{"_id":"124944217","date":"1602496532","price":0.0044193,"pair":"ltcbtc","amount":29.91323,"__v":0},{"_id":"124944220","date":"1602496532","price":0.00441932,"pair":"ltcbtc","amount":99.606,"__v":0},{"_id":"124944685","date":"1602497238","price":0.00443023,"pair":"ltcbtc","amount":2.274741,"__v":0},{"_id":"124944768","date":"1602497364","price":0.00443101,"pair":"ltcbtc","amount":0.504063,"__v":0},{"_id":"124945068","date":"1602498019","price":0.00442776,"pair":"ltcbtc","amount":14.702113,"__v":0},{"_id":"124945081","date":"1602498048","price":0.00442202,"pair":"ltcbtc","amount":1.022033,"__v":0},{"_id":"124945114","date":"1602498128","price":0.00442739,"pair":"ltcbtc","amount":3.62761,"__v":0},{"_id":"124945382","date":"1602498562","price":0.00441651,"pair":"ltcbtc","amount":8.76793893,"__v":0},{"_id":"124945922","date":"1602499190","price":0.0044148,"pair":"ltcbtc","amount":0.268795,"__v":0},{"_id":"124946022","date":"1602499309","price":0.00440549,"pair":"ltcbtc","amount":38.105,"__v":0},{"_id":"124946025","date":"1602499309","price":0.00440111,"pair":"ltcbtc","amount":2.148302,"__v":0},{"_id":"124946024","date":"1602499309","price":0.00440317,"pair":"ltcbtc","amount":30.10508,"__v":0},{"_id":"124946023","date":"1602499309","price":0.0044043,"pair":"ltcbtc","amount":30.09736,"__v":0},{"_id":"124946044","date":"1602499330","price":0.00441464,"pair":"ltcbtc","amount":16.323703,"__v":0},{"_id":"124946397","date":"1602499366","price":0.00439978,"pair":"ltcbtc","amount":30.18,"__v":0},{"_id":"124947704","date":"1602499421","price":0.00441605,"pair":"ltcbtc","amount":37.28,"__v":0},{"_id":"124947716","date":"1602499421","price":0.00441605,"pair":"ltcbtc","amount":0.004,"__v":0},{"_id":"124948130","date":"1602499556","price":0.00442219,"pair":"ltcbtc","amount":60,"__v":0},{"_id":"124948186","date":"1602499579","price":0.00441613,"pair":"ltcbtc","amount":0.25441,"__v":0},{"_id":"124949008","date":"1602500070","price":0.00441243,"pair":"ltcbtc","amount":1.690864,"__v":0},{"_id":"124949041","date":"1602500125","price":0.00441243,"pair":"ltcbtc","amount":0.622713,"__v":0},{"_id":"124949086","date":"1602500163","price":0.00441363,"pair":"ltcbtc","amount":0.58000967,"__v":0},{"_id":"124949257","date":"1602500281","price":0.00441494,"pair":"ltcbtc","amount":3.098787,"__v":0},{"_id":"124950316","date":"1602501535","price":0.00440713,"pair":"ltcbtc","amount":0.248403,"__v":0},{"_id":"124950835","date":"1602502280","price":0.00440386,"pair":"ltcbtc","amount":1.964154,"__v":0},{"_id":"124950867","date":"1602502339","price":0.00440167,"pair":"ltcbtc","amount":0.458245,"__v":0},{"_id":"124951140","date":"1602502700","price":0.00439764,"pair":"ltcbtc","amount":0.357294,"__v":0},{"_id":"124951435","date":"1602503063","price":0.00440552,"pair":"ltcbtc","amount":1.508802,"__v":0},{"_id":"124951594","date":"1602503307","price":0.00439738,"pair":"ltcbtc","amount":23.546905,"__v":0},{"_id":"124951967","date":"1602503806","price":0.0044086,"pair":"ltcbtc","amount":8.1464,"__v":0},{"_id":"124952214","date":"1602504170","price":0.00440339,"pair":"ltcbtc","amount":100.833,"__v":0},{"_id":"124952262","date":"1602504206","price":0.00440794,"pair":"ltcbtc","amount":0.573541,"__v":0},{"_id":"124953294","date":"1602505684","price":0.00440105,"pair":"ltcbtc","amount":30.22748,"__v":0},{"_id":"124953718","date":"1602506261","price":0.0044065,"pair":"ltcbtc","amount":1.053027,"__v":0},{"_id":"124953930","date":"1602506440","price":0.00440705,"pair":"ltcbtc","amount":1.21,"__v":0},{"_id":"124954012","date":"1602506490","price":0.00440775,"pair":"ltcbtc","amount":2.649121,"__v":0},{"_id":"124954506","date":"1602507136","price":0.00442668,"pair":"ltcbtc","amount":100.013,"__v":0},{"_id":"124954926","date":"1602507724","price":0.00444274,"pair":"ltcbtc","amount":20,"__v":0},{"_id":"124954991","date":"1602507828","price":0.00443233,"pair":"ltcbtc","amount":99.829,"__v":0},{"_id":"124955969","date":"1602508658","price":0.00442997,"pair":"ltcbtc","amount":5.691667,"__v":0},{"_id":"124956143","date":"1602508851","price":0.00442692,"pair":"ltcbtc","amount":0.23639,"__v":0},{"_id":"124956266","date":"1602508997","price":0.00442572,"pair":"ltcbtc","amount":2.563773,"__v":0},{"_id":"124956355","date":"1602509179","price":0.00442555,"pair":"ltcbtc","amount":9.9,"__v":0},{"_id":"124956356","date":"1602509179","price":0.00442555,"pair":"ltcbtc","amount":89.965,"__v":0},{"_id":"124956358","date":"1602509181","price":0.00443,"pair":"ltcbtc","amount":9.456,"__v":0},{"_id":"124956359","date":"1602509181","price":0.00443,"pair":"ltcbtc","amount":0.000003,"__v":0},{"_id":"124956453","date":"1602509316","price":0.00442661,"pair":"ltcbtc","amount":0.250139,"__v":0},{"_id":"124957084","date":"1602509637","price":0.00443232,"pair":"ltcbtc","amount":0.524704,"__v":0},{"_id":"124958684","date":"1602509970","price":0.0044553,"pair":"ltcbtc","amount":2.166618,"__v":0},{"_id":"124959242","date":"1602510173","price":0.00445381,"pair":"ltcbtc","amount":1.167396,"__v":0},{"_id":"124959280","date":"1602510198","price":0.00445722,"pair":"ltcbtc","amount":1.226678,"__v":0},{"_id":"124959286","date":"1602510201","price":0.00446809,"pair":"ltcbtc","amount":0.443598,"__v":0},{"_id":"124959915","date":"1602510353","price":0.00446001,"pair":"ltcbtc","amount":29.42978,"__v":0},{"_id":"124959916","date":"1602510353","price":0.00446001,"pair":"ltcbtc","amount":42.60542,"__v":0},{"_id":"124960975","date":"1602510524","price":0.0044572,"pair":"ltcbtc","amount":0.51360814,"__v":0},{"_id":"124960993","date":"1602510536","price":0.00445452,"pair":"ltcbtc","amount":5.61733697,"__v":0},{"_id":"124961098","date":"1602510555","price":0.00445452,"pair":"ltcbtc","amount":5.61921678,"__v":0},{"_id":"124961305","date":"1602510585","price":0.00445461,"pair":"ltcbtc","amount":5.61648332,"__v":0},{"_id":"124961366","date":"1602510612","price":0.0044532,"pair":"ltcbtc","amount":5.670647,"__v":0},{"_id":"124961424","date":"1602510630","price":0.00445485,"pair":"ltcbtc","amount":5.66854669,"__v":0},{"_id":"124961526","date":"1602510658","price":0.00445555,"pair":"ltcbtc","amount":0.5,"__v":0},{"_id":"124961527","date":"1602510658","price":0.00445554,"pair":"ltcbtc","amount":0.00504823,"__v":0},{"_id":"124962331","date":"1602510987","price":0.00443778,"pair":"ltcbtc","amount":97.938,"__v":0},{"_id":"124962397","date":"1602511028","price":0.00443194,"pair":"ltcbtc","amount":5.837353,"__v":0},{"_id":"124963316","date":"1602511560","price":0.00441988,"pair":"ltcbtc","amount":0.26362,"__v":0},{"_id":"124963404","date":"1602511629","price":0.00442295,"pair":"ltcbtc","amount":1.184937,"__v":0},{"_id":"124963442","date":"1602511668","price":0.00443282,"pair":"ltcbtc","amount":1.85511081,"__v":0},{"_id":"124963729","date":"1602511867","price":0.00442211,"pair":"ltcbtc","amount":1.308084,"__v":0},{"_id":"124964937","date":"1602512580","price":0.00442717,"pair":"ltcbtc","amount":0.5,"__v":0},{"_id":"124964938","date":"1602512580","price":0.00442648,"pair":"ltcbtc","amount":0.5,"__v":0},{"_id":"124964941","date":"1602512580","price":0.00442644,"pair":"ltcbtc","amount":0.22,"__v":0},{"_id":"124964940","date":"1602512580","price":0.00442646,"pair":"ltcbtc","amount":0.5,"__v":0},{"_id":"124964939","date":"1602512580","price":0.00442647,"pair":"ltcbtc","amount":0.5,"__v":0},{"_id":"124965032","date":"1602512669","price":0.00442392,"pair":"ltcbtc","amount":0.30438,"__v":0},{"_id":"124965037","date":"1602512675","price":0.00442392,"pair":"ltcbtc","amount":0.685929,"__v":0},{"_id":"124965195","date":"1602512820","price":0.00442649,"pair":"ltcbtc","amount":6.804731,"__v":0},{"_id":"124965379","date":"1602512977","price":0.0044279,"pair":"ltcbtc","amount":5.84526,"__v":0},{"_id":"124965444","date":"1602513051","price":0.00443636,"pair":"ltcbtc","amount":56.91,"__v":0},{"_id":"124965553","date":"1602513126","price":0.00442691,"pair":"ltcbtc","amount":2.506409,"__v":0},{"_id":"124965591","date":"1602513169","price":0.00442916,"pair":"ltcbtc","amount":1,"__v":0},{"_id":"124965971","date":"1602513492","price":0.00442747,"pair":"ltcbtc","amount":1.53591238,"__v":0},{"_id":"124966131","date":"1602513638","price":0.00443067,"pair":"ltcbtc","amount":70.927604,"__v":0},{"_id":"124966129","date":"1602513638","price":0.00443067,"pair":"ltcbtc","amount":29.55571,"__v":0},{"_id":"124966130","date":"1602513638","price":0.00443067,"pair":"ltcbtc","amount":0.5,"__v":0},{"_id":"124966193","date":"1602513727","price":0.00442168,"pair":"ltcbtc","amount":0.781099,"__v":0},{"_id":"124966688","date":"1602514183","price":0.00441624,"pair":"ltcbtc","amount":0.90216216,"__v":0},{"_id":"124966752","date":"1602514263","price":0.00442429,"pair":"ltcbtc","amount":0.563842,"__v":0},{"_id":"124966893","date":"1602514350","price":0.00442194,"pair":"ltcbtc","amount":0.435693,"__v":0},{"_id":"124968149","date":"1602515698","price":0.00441951,"pair":"ltcbtc","amount":2.24369512,"__v":0},{"_id":"124968449","date":"1602516011","price":0.00442005,"pair":"ltcbtc","amount":7.736172,"__v":0},{"_id":"124968447","date":"1602516011","price":0.00442098,"pair":"ltcbtc","amount":0.5,"__v":0},{"_id":"124968448","date":"1602516011","price":0.00442082,"pair":"ltcbtc","amount":29.49171,"__v":0},{"_id":"124968568","date":"1602516192","price":0.00441904,"pair":"ltcbtc","amount":0.423846,"__v":0},{"_id":"124969189","date":"1602516585","price":0.00441511,"pair":"ltcbtc","amount":2.31967,"__v":0},{"_id":"124969188","date":"1602516585","price":0.00441511,"pair":"ltcbtc","amount":8.59109,"__v":0},{"_id":"124969187","date":"1602516585","price":0.00441511,"pair":"ltcbtc","amount":12.14333,"__v":0},{"_id":"124969185","date":"1602516585","price":0.00441511,"pair":"ltcbtc","amount":52.96367,"__v":0},{"_id":"124969186","date":"1602516585","price":0.00441511,"pair":"ltcbtc","amount":3.88964,"__v":0},{"_id":"124969183","date":"1602516585","price":0.00441511,"pair":"ltcbtc","amount":11.94866,"__v":0},{"_id":"124969182","date":"1602516585","price":0.00441511,"pair":"ltcbtc","amount":1.47114,"__v":0},{"_id":"124969184","date":"1602516585","price":0.00441511,"pair":"ltcbtc","amount":4.7968,"__v":0},{"_id":"124969863","date":"1602516866","price":0.0044042,"pair":"ltcbtc","amount":21.58837488,"__v":0},{"_id":"124969862","date":"1602516866","price":0.00440498,"pair":"ltcbtc","amount":7.9,"__v":0},{"_id":"124970052","date":"1602516875","price":0.00439782,"pair":"ltcbtc","amount":22.40849,"__v":0},{"_id":"124970053","date":"1602516875","price":0.00439782,"pair":"ltcbtc","amount":9.85451,"__v":0},{"_id":"124970142","date":"1602516880","price":0.00439523,"pair":"ltcbtc","amount":17.23416984,"__v":0},{"_id":"124970177","date":"1602516882","price":0.00439436,"pair":"ltcbtc","amount":15.8,"__v":0},{"_id":"124970194","date":"1602516883","price":0.00439436,"pair":"ltcbtc","amount":4.344,"__v":0},{"_id":"124970197","date":"1602516883","price":0.00439436,"pair":"ltcbtc","amount":4.80243,"__v":0},{"_id":"124970224","date":"1602516892","price":0.00439437,"pair":"ltcbtc","amount":32.68099,"__v":0},{"_id":"124970222","date":"1602516892","price":0.00439437,"pair":"ltcbtc","amount":2.31001,"__v":0},{"_id":"124970291","date":"1602516898","price":0.00439,"pair":"ltcbtc","amount":6.45,"__v":0},{"_id":"124970302","date":"1602516900","price":0.00439437,"pair":"ltcbtc","amount":13.0984,"__v":0},{"_id":"124970628","date":"1602516959","price":0.0044072,"pair":"ltcbtc","amount":7.63402,"__v":0},{"_id":"124971182","date":"1602517345","price":0.00441342,"pair":"ltcbtc","amount":15,"__v":0},{"_id":"124971445","date":"1602517642","price":0.00440522,"pair":"ltcbtc","amount":2.85772,"__v":0},{"_id":"124972032","date":"1602518165","price":0.00441863,"pair":"ltcbtc","amount":0.231857,"__v":0},{"_id":"124972114","date":"1602518334","price":0.004415,"pair":"ltcbtc","amount":0.231829,"__v":0},{"_id":"124973511","date":"1602519433","price":0.00441,"pair":"ltcbtc","amount":0.636,"__v":0},{"_id":"124973518","date":"1602519451","price":0.00441,"pair":"ltcbtc","amount":0.000212,"__v":0},{"_id":"124973530","date":"1602519468","price":0.00441028,"pair":"ltcbtc","amount":0.361612,"__v":0},{"_id":"124973657","date":"1602519588","price":0.00441,"pair":"ltcbtc","amount":0.884476,"__v":0},{"_id":"124973894","date":"1602519768","price":0.00441146,"pair":"ltcbtc","amount":0.257502,"__v":0},{"_id":"124974560","date":"1602520366","price":0.00441968,"pair":"ltcbtc","amount":2.228562,"__v":0},{"_id":"124975361","date":"1602521150","price":0.00442924,"pair":"ltcbtc","amount":4.97,"__v":0},{"_id":"124975479","date":"1602521247","price":0.00442825,"pair":"ltcbtc","amount":0.9,"__v":0},{"_id":"124975482","date":"1602521250","price":0.00442826,"pair":"ltcbtc","amount":4.79594752,"__v":0},{"_id":"124975634","date":"1602521429","price":0.00442585,"pair":"ltcbtc","amount":0.273929,"__v":0},{"_id":"124975988","date":"1602521732","price":0.00443313,"pair":"ltcbtc","amount":2.576008,"__v":0},{"_id":"124975987","date":"1602521732","price":0.00443236,"pair":"ltcbtc","amount":0.5,"__v":0},{"_id":"124975986","date":"1602521732","price":0.00443207,"pair":"ltcbtc","amount":0.5,"__v":0},{"_id":"124975985","date":"1602521732","price":0.00443206,"pair":"ltcbtc","amount":0.5,"__v":0},{"_id":"124975984","date":"1602521732","price":0.00443145,"pair":"ltcbtc","amount":0.5,"__v":0},{"_id":"124976177","date":"1602521943","price":0.00442873,"pair":"ltcbtc","amount":61.44478,"__v":0},{"_id":"124976418","date":"1602522100","price":0.00442803,"pair":"ltcbtc","amount":3.2357,"__v":0},{"_id":"124977077","date":"1602522591","price":0.00443066,"pair":"ltcbtc","amount":0.461152,"__v":0},{"_id":"124977103","date":"1602522628","price":0.00443,"pair":"ltcbtc","amount":4.33589,"__v":0},{"_id":"124977189","date":"1602522717","price":0.00442933,"pair":"ltcbtc","amount":0.335679,"__v":0},{"_id":"124977207","date":"1602522731","price":0.00443,"pair":"ltcbtc","amount":0.000006,"__v":0},{"_id":"124978149","date":"1602523100","price":0.00442746,"pair":"ltcbtc","amount":0.38697,"__v":0},{"_id":"124978566","date":"1602523310","price":0.00443,"pair":"ltcbtc","amount":580.23,"__v":0},{"_id":"124978591","date":"1602523324","price":0.00443,"pair":"ltcbtc","amount":51.69,"__v":0},{"_id":"124979732","date":"1602524048","price":0.00441414,"pair":"ltcbtc","amount":7.9,"__v":0},{"_id":"124979733","date":"1602524048","price":0.00441414,"pair":"ltcbtc","amount":0.5,"__v":0},{"_id":"124979734","date":"1602524048","price":0.00441413,"pair":"ltcbtc","amount":0.5,"__v":0},{"_id":"124979735","date":"1602524048","price":0.00441292,"pair":"ltcbtc","amount":31.928,"__v":0},{"_id":"124979736","date":"1602524048","price":0.0044128,"pair":"ltcbtc","amount":29.43934,"__v":0},{"_id":"124979737","date":"1602524048","price":0.00441252,"pair":"ltcbtc","amount":29.40014,"__v":0},{"_id":"124979738","date":"1602524048","price":0.0044124,"pair":"ltcbtc","amount":97.991,"__v":0},{"_id":"124979739","date":"1602524048","price":0.00441226,"pair":"ltcbtc","amount":196,"__v":0},{"_id":"124979740","date":"1602524048","price":0.00441161,"pair":"ltcbtc","amount":29.40586,"__v":0},{"_id":"124979741","date":"1602524048","price":0.00441065,"pair":"ltcbtc","amount":141.81337763,"__v":0},{"_id":"124979805","date":"1602524081","price":0.0044146,"pair":"ltcbtc","amount":0.289706,"__v":0},{"_id":"124980941","date":"1602524640","price":0.00442045,"pair":"ltcbtc","amount":7.86874,"__v":0},{"_id":"124981636","date":"1602525006","price":0.00442551,"pair":"ltcbtc","amount":46.271722,"__v":0},{"_id":"124981668","date":"1602525035","price":0.00442153,"pair":"ltcbtc","amount":0.93166,"__v":0},{"_id":"124982169","date":"1602525308","price":0.00442453,"pair":"ltcbtc","amount":8.782654,"__v":0},{"_id":"124983068","date":"1602525771","price":0.004431,"pair":"ltcbtc","amount":1.9913,"__v":0},{"_id":"124983100","date":"1602525799","price":0.004431,"pair":"ltcbtc","amount":0.000008,"__v":0},{"_id":"124983463","date":"1602526093","price":0.00442846,"pair":"ltcbtc","amount":2.266549,"__v":0},{"_id":"124983888","date":"1602526198","price":0.0044211,"pair":"ltcbtc","amount":4.080745,"__v":0},{"_id":"124986144","date":"1602528173","price":0.00442689,"pair":"ltcbtc","amount":0.247324,"__v":0},{"_id":"124986958","date":"1602529331","price":0.00442877,"pair":"ltcbtc","amount":3.065355,"__v":0},{"_id":"124987086","date":"1602529517","price":0.00443244,"pair":"ltcbtc","amount":0.332154,"__v":0},{"_id":"124987860","date":"1602530092","price":0.00443319,"pair":"ltcbtc","amount":2.277001,"__v":0},{"_id":"124987900","date":"1602530162","price":0.0044338,"pair":"ltcbtc","amount":0.5,"__v":0},{"_id":"124987901","date":"1602530162","price":0.00443372,"pair":"ltcbtc","amount":0.3,"__v":0},{"_id":"124988046","date":"1602530252","price":0.0044332,"pair":"ltcbtc","amount":0.358,"__v":0},{"_id":"124988107","date":"1602530291","price":0.0044332,"pair":"ltcbtc","amount":0.00017,"__v":0},{"_id":"124988761","date":"1602530609","price":0.00443542,"pair":"ltcbtc","amount":0.403634,"__v":0},{"_id":"124988949","date":"1602530807","price":0.00443525,"pair":"ltcbtc","amount":0.430289,"__v":0},{"_id":"124989113","date":"1602530961","price":0.00443124,"pair":"ltcbtc","amount":1.494694,"__v":0},{"_id":"124989444","date":"1602531326","price":0.00442885,"pair":"ltcbtc","amount":2.04014,"__v":0},{"_id":"124989457","date":"1602531355","price":0.0044284,"pair":"ltcbtc","amount":1.438,"__v":0},{"_id":"124989455","date":"1602531355","price":0.0044284,"pair":"ltcbtc","amount":92.82188,"__v":0},{"_id":"124989583","date":"1602531545","price":0.00442226,"pair":"ltcbtc","amount":3.207249,"__v":0},{"_id":"124989652","date":"1602531629","price":0.00442505,"pair":"ltcbtc","amount":0.36461,"__v":0},{"_id":"124989651","date":"1602531629","price":0.00442445,"pair":"ltcbtc","amount":0.5,"__v":0},{"_id":"124989764","date":"1602531769","price":0.00442033,"pair":"ltcbtc","amount":0.86461,"__v":0},{"_id":"124989806","date":"1602531822","price":0.00442387,"pair":"ltcbtc","amount":0.750966,"__v":0},{"_id":"124989831","date":"1602531854","price":0.0044247,"pair":"ltcbtc","amount":23.130693,"__v":0},{"_id":"124989885","date":"1602531932","price":0.00442034,"pair":"ltcbtc","amount":0.244154,"__v":0},{"_id":"124990022","date":"1602531993","price":0.00441883,"pair":"ltcbtc","amount":0.477179,"__v":0},{"_id":"124990191","date":"1602532125","price":0.00441981,"pair":"ltcbtc","amount":1.320517,"__v":0},{"_id":"124991190","date":"1602532839","price":0.00442644,"pair":"ltcbtc","amount":0.5,"__v":0},{"_id":"124991191","date":"1602532839","price":0.00442686,"pair":"ltcbtc","amount":1.985477,"__v":0},{"_id":"124991544","date":"1602533313","price":0.00442796,"pair":"ltcbtc","amount":0.431498,"__v":0},{"_id":"124991658","date":"1602533602","price":0.00442132,"pair":"ltcbtc","amount":2.037674,"__v":0},{"_id":"124991657","date":"1602533602","price":0.00442155,"pair":"ltcbtc","amount":0.5,"__v":0},{"_id":"124991654","date":"1602533602","price":0.00442236,"pair":"ltcbtc","amount":0.5,"__v":0},{"_id":"124991655","date":"1602533602","price":0.00442231,"pair":"ltcbtc","amount":0.5,"__v":0},{"_id":"124991656","date":"1602533602","price":0.00442156,"pair":"ltcbtc","amount":0.5,"__v":0},{"_id":"124991815","date":"1602533931","price":0.00442845,"pair":"ltcbtc","amount":97.697,"__v":0},{"_id":"124992339","date":"1602534878","price":0.00441703,"pair":"ltcbtc","amount":8.50000003,"__v":0},{"_id":"124992914","date":"1602535706","price":0.00441699,"pair":"ltcbtc","amount":97.961,"__v":0},{"_id":"124996305","date":"1602538381","price":0.00439164,"pair":"ltcbtc","amount":10,"__v":0},{"_id":"124997584","date":"1602538923","price":0.00439275,"pair":"ltcbtc","amount":0.904831,"__v":0},{"_id":"124997864","date":"1602539150","price":0.00439342,"pair":"ltcbtc","amount":0.035724,"__v":0},{"_id":"124997863","date":"1602539150","price":0.00439343,"pair":"ltcbtc","amount":0.366,"__v":0},{"_id":"124998089","date":"1602539377","price":0.00439048,"pair":"ltcbtc","amount":1.24999544,"__v":0},{"_id":"124998139","date":"1602539491","price":0.00438414,"pair":"ltcbtc","amount":14.003053,"__v":0},{"_id":"124998145","date":"1602539511","price":0.0043909,"pair":"ltcbtc","amount":97.424,"__v":0},{"_id":"124998149","date":"1602539511","price":0.00439188,"pair":"ltcbtc","amount":9.8995,"__v":0},{"_id":"124998148","date":"1602539511","price":0.00439188,"pair":"ltcbtc","amount":5.23037,"__v":0},{"_id":"124998147","date":"1602539511","price":0.00439188,"pair":"ltcbtc","amount":4.87013,"__v":0},{"_id":"124998239","date":"1602539586","price":0.004396,"pair":"ltcbtc","amount":0.000136,"__v":0},{"_id":"124998238","date":"1602539586","price":0.004396,"pair":"ltcbtc","amount":1.421,"__v":0},{"_id":"124998282","date":"1602539683","price":0.00439484,"pair":"ltcbtc","amount":1.28199544,"__v":0},{"_id":"124998734","date":"1602539815","price":0.00439691,"pair":"ltcbtc","amount":0.65493,"__v":0},{"_id":"124999380","date":"1602540133","price":0.00440843,"pair":"ltcbtc","amount":0.25,"__v":0},{"_id":"125001935","date":"1602541511","price":0.00439773,"pair":"ltcbtc","amount":5,"__v":0},{"_id":"125002196","date":"1602541717","price":0.00439,"pair":"ltcbtc","amount":0.430289,"__v":0},{"_id":"125003329","date":"1602542393","price":0.00439231,"pair":"ltcbtc","amount":1.489366,"__v":0},{"_id":"125003422","date":"1602542485","price":0.00439637,"pair":"ltcbtc","amount":0.303942,"__v":0},{"_id":"125004045","date":"1602542686","price":0.00440304,"pair":"ltcbtc","amount":62.506733,"__v":0},{"_id":"125004044","date":"1602542686","price":0.00440304,"pair":"ltcbtc","amount":29.1902,"__v":0},{"_id":"125004042","date":"1602542686","price":0.00440194,"pair":"ltcbtc","amount":7.9,"__v":0},{"_id":"125004043","date":"1602542686","price":0.00440194,"pair":"ltcbtc","amount":0.5,"__v":0},{"_id":"125005473","date":"1602544188","price":0.00439593,"pair":"ltcbtc","amount":29.31931,"__v":0},{"_id":"125005484","date":"1602544188","price":0.00439592,"pair":"ltcbtc","amount":12.837,"__v":0},{"_id":"125005588","date":"1602544191","price":0.00439987,"pair":"ltcbtc","amount":29.26665,"__v":0},{"_id":"125005705","date":"1602544197","price":0.00439712,"pair":"ltcbtc","amount":49.31372,"__v":0},{"_id":"125005724","date":"1602544198","price":0.00439525,"pair":"ltcbtc","amount":2.95773847,"__v":0},{"_id":"125005743","date":"1602544199","price":0.0043916,"pair":"ltcbtc","amount":0.5,"__v":0},{"_id":"125005840","date":"1602544210","price":0.00439987,"pair":"ltcbtc","amount":3.4392,"__v":0},{"_id":"125006806","date":"1602545009","price":0.00438548,"pair":"ltcbtc","amount":0.494136,"__v":0},{"_id":"125007159","date":"1602545633","price":0.00438018,"pair":"ltcbtc","amount":0.28188345,"__v":0},{"_id":"125007307","date":"1602545867","price":0.00438332,"pair":"ltcbtc","amount":1.19,"__v":0},{"_id":"125007926","date":"1602546908","price":0.00438517,"pair":"ltcbtc","amount":1.009,"__v":0},{"_id":"125008002","date":"1602547100","price":0.00438836,"pair":"ltcbtc","amount":0.5,"__v":0},{"_id":"125008003","date":"1602547100","price":0.00438847,"pair":"ltcbtc","amount":0.151216,"__v":0},{"_id":"125007999","date":"1602547100","price":0.00438749,"pair":"ltcbtc","amount":0.5,"__v":0},{"_id":"125008001","date":"1602547100","price":0.00438813,"pair":"ltcbtc","amount":0.5,"__v":0},{"_id":"125007998","date":"1602547100","price":0.00438748,"pair":"ltcbtc","amount":0.5,"__v":0},{"_id":"125008000","date":"1602547100","price":0.00438812,"pair":"ltcbtc","amount":0.5,"__v":0}]